{"block_number":23028070,"execution_time_ms":7725,"opportunities_found":0,"proactive_opportunities_found":0,"reactive_opportunities_found":0,"hot_token_opportunities_found":0,"cross_dex_opportunities_found":0,"trades_executed":[],"errors":[],"mev_attacks":[],"competition_results":[],"scan_metrics":{"proactive_opportunities":0,"reactive_opportunities":0,"hot_token_opportunities":0,"cross_dex_opportunities":0,"total_scan_time_ms":7719}}
{"block_number":23028071,"execution_time_ms":5479,"opportunities_found":0,"proactive_opportunities_found":0,"reactive_opportunities_found":0,"hot_token_opportunities_found":0,"cross_dex_opportunities_found":0,"trades_executed":[],"errors":[],"mev_attacks":[],"competition_results":[],"scan_metrics":{"proactive_opportunities":0,"reactive_opportunities":0,"hot_token_opportunities":0,"cross_dex_opportunities":0,"total_scan_time_ms":5478}}
{"block_number":23028072,"execution_time_ms":4591,"opportunities_found":0,"proactive_opportunities_found":0,"reactive_opportunities_found":0,"hot_token_opportunities_found":0,"cross_dex_opportunities_found":0,"trades_executed":[],"errors":[],"mev_attacks":[],"competition_results":[],"scan_metrics":{"proactive_opportunities":0,"reactive_opportunities":0,"hot_token_opportunities":0,"cross_dex_opportunities":0,"total_scan_time_ms":4589}}
{"block_number":23028073,"execution_time_ms":3966,"opportunities_found":0,"proactive_opportunities_found":0,"reactive_opportunities_found":0,"hot_token_opportunities_found":0,"cross_dex_opportunities_found":0,"trades_executed":[],"errors":[],"mev_attacks":[],"competition_results":[],"scan_metrics":{"proactive_opportunities":0,"reactive_opportunities":0,"hot_token_opportunities":0,"cross_dex_opportunities":0,"total_scan_time_ms":3965}}
{"block_number":23028074,"execution_time_ms":4606,"opportunities_found":0,"proactive_opportunities_found":0,"reactive_opportunities_found":0,"hot_token_opportunities_found":0,"cross_dex_opportunities_found":0,"trades_executed":[],"errors":[],"mev_attacks":[],"competition_results":[],"scan_metrics":{"proactive_opportunities":0,"reactive_opportunities":0,"hot_token_opportunities":0,"cross_dex_opportunities":0,"total_scan_time_ms":4605}}
{"block_number":23028075,"execution_time_ms":5857,"opportunities_found":0,"proactive_opportunities_found":0,"reactive_opportunities_found":0,"hot_token_opportunities_found":0,"cross_dex_opportunities_found":0,"trades_executed":[],"errors":[],"mev_attacks":[],"competition_results":[],"scan_metrics":{"proactive_opportunities":0,"reactive_opportunities":0,"hot_token_opportunities":0,"cross_dex_opportunities":0,"total_scan_time_ms":5856}}
{"block_number":23028076,"execution_time_ms":2627,"opportunities_found":0,"proactive_opportunities_found":0,"reactive_opportunities_found":0,"hot_token_opportunities_found":0,"cross_dex_opportunities_found":0,"trades_executed":[],"errors":[],"mev_attacks":[],"competition_results":[],"scan_metrics":{"proactive_opportunities":0,"reactive_opportunities":0,"hot_token_opportunities":0,"cross_dex_opportunities":0,"total_scan_time_ms":2626}}
{"block_number":23028077,"execution_time_ms":4241,"opportunities_found":0,"proactive_opportunities_found":0,"reactive_opportunities_found":0,"hot_token_opportunities_found":0,"cross_dex_opportunities_found":0,"trades_executed":[],"errors":[],"mev_attacks":[],"competition_results":[],"scan_metrics":{"proactive_opportunities":0,"reactive_opportunities":0,"hot_token_opportunities":0,"cross_dex_opportunities":0,"total_scan_time_ms":4240}}
{"block_number":23028078,"execution_time_ms":3259,"opportunities_found":0,"proactive_opportunities_found":0,"reactive_opportunities_found":0,"hot_token_opportunities_found":0,"cross_dex_opportunities_found":0,"trades_executed":[],"errors":[],"mev_attacks":[],"competition_results":[],"scan_metrics":{"proactive_opportunities":0,"reactive_opportunities":0,"hot_token_opportunities":0,"cross_dex_opportunities":0,"total_scan_time_ms":3258}}
{"block_number":23028079,"execution_time_ms":2990,"opportunities_found":0,"proactive_opportunities_found":0,"reactive_opportunities_found":0,"hot_token_opportunities_found":0,"cross_dex_opportunities_found":0,"trades_executed":[],"errors":[],"mev_attacks":[],"competition_results":[],"scan_metrics":{"proactive_opportunities":0,"reactive_opportunities":0,"hot_token_opportunities":0,"cross_dex_opportunities":0,"total_scan_time_ms":2989}}
{"block_number":23028080,"execution_time_ms":4272,"opportunities_found":0,"proactive_opportunities_found":0,"reactive_opportunities_found":0,"hot_token_opportunities_found":0,"cross_dex_opportunities_found":0,"trades_executed":[],"errors":[],"mev_attacks":[],"competition_results":[],"scan_metrics":{"proactive_opportunities":0,"reactive_opportunities":0,"hot_token_opportunities":0,"cross_dex_opportunities":0,"total_scan_time_ms":4271}}
{"block_number":23028081,"execution_time_ms":1306,"opportunities_found":0,"proactive_opportunities_found":0,"reactive_opportunities_found":0,"hot_token_opportunities_found":0,"cross_dex_opportunities_found":0,"trades_executed":[],"errors":[],"mev_attacks":[],"competition_results":[],"scan_metrics":{"proactive_opportunities":0,"reactive_opportunities":0,"hot_token_opportunities":0,"cross_dex_opportunities":0,"total_scan_time_ms":1306}}
{"block_number":23028082,"execution_time_ms":5818,"opportunities_found":0,"proactive_opportunities_found":0,"reactive_opportunities_found":0,"hot_token_opportunities_found":0,"cross_dex_opportunities_found":0,"trades_executed":[],"errors":[],"mev_attacks":[],"competition_results":[],"scan_metrics":{"proactive_opportunities":0,"reactive_opportunities":0,"hot_token_opportunities":0,"cross_dex_opportunities":0,"total_scan_time_ms":5817}}
{"block_number":23028083,"execution_time_ms":2924,"opportunities_found":0,"proactive_opportunities_found":0,"reactive_opportunities_found":0,"hot_token_opportunities_found":0,"cross_dex_opportunities_found":0,"trades_executed":[],"errors":[],"mev_attacks":[],"competition_results":[],"scan_metrics":{"proactive_opportunities":0,"reactive_opportunities":0,"hot_token_opportunities":0,"cross_dex_opportunities":0,"total_scan_time_ms":2923}}
{"block_number":23028084,"execution_time_ms":3243,"opportunities_found":0,"proactive_opportunities_found":0,"reactive_opportunities_found":0,"hot_token_opportunities_found":0,"cross_dex_opportunities_found":0,"trades_executed":[],"errors":[],"mev_attacks":[],"competition_results":[],"scan_metrics":{"proactive_opportunities":0,"reactive_opportunities":0,"hot_token_opportunities":0,"cross_dex_opportunities":0,"total_scan_time_ms":3242}}
{"block_number":23028085,"execution_time_ms":5215,"opportunities_found":0,"proactive_opportunities_found":0,"reactive_opportunities_found":0,"hot_token_opportunities_found":0,"cross_dex_opportunities_found":0,"trades_executed":[],"errors":[],"mev_attacks":[],"competition_results":[],"scan_metrics":{"proactive_opportunities":0,"reactive_opportunities":0,"hot_token_opportunities":0,"cross_dex_opportunities":0,"total_scan_time_ms":5214}}
{"block_number":23028086,"execution_time_ms":1618,"opportunities_found":0,"proactive_opportunities_found":0,"reactive_opportunities_found":0,"hot_token_opportunities_found":0,"cross_dex_opportunities_found":0,"trades_executed":[],"errors":[],"mev_attacks":[],"competition_results":[],"scan_metrics":{"proactive_opportunities":0,"reactive_opportunities":0,"hot_token_opportunities":0,"cross_dex_opportunities":0,"total_scan_time_ms":1616}}
{"block_number":23028087,"execution_time_ms":4127,"opportunities_found":0,"proactive_opportunities_found":0,"reactive_opportunities_found":0,"hot_token_opportunities_found":0,"cross_dex_opportunities_found":0,"trades_executed":[],"errors":[],"mev_attacks":[],"competition_results":[],"scan_metrics":{"proactive_opportunities":0,"reactive_opportunities":0,"hot_token_opportunities":0,"cross_dex_opportunities":0,"total_scan_time_ms":4121}}
{"block_number":23028088,"execution_time_ms":3819,"opportunities_found":0,"proactive_opportunities_found":0,"reactive_opportunities_found":0,"hot_token_opportunities_found":0,"cross_dex_opportunities_found":0,"trades_executed":[],"errors":[],"mev_attacks":[],"competition_results":[],"scan_metrics":{"proactive_opportunities":0,"reactive_opportunities":0,"hot_token_opportunities":0,"cross_dex_opportunities":0,"total_scan_time_ms":3817}}
{"block_number":23028089,"execution_time_ms":3624,"opportunities_found":0,"proactive_opportunities_found":0,"reactive_opportunities_found":0,"hot_token_opportunities_found":0,"cross_dex_opportunities_found":0,"trades_executed":[],"errors":[],"mev_attacks":[],"competition_results":[],"scan_metrics":{"proactive_opportunities":0,"reactive_opportunities":0,"hot_token_opportunities":0,"cross_dex_opportunities":0,"total_scan_time_ms":3621}}
{"block_number":23028090,"execution_time_ms":14094,"opportunities_found":0,"proactive_opportunities_found":0,"reactive_opportunities_found":0,"hot_token_opportunities_found":0,"cross_dex_opportunities_found":0,"trades_executed":[],"errors":[],"mev_attacks":[],"competition_results":[],"scan_metrics":{"proactive_opportunities":0,"reactive_opportunities":0,"hot_token_opportunities":0,"cross_dex_opportunities":0,"total_scan_time_ms":14092}}
{"block_number":23028091,"execution_time_ms":5937,"opportunities_found":0,"proactive_opportunities_found":0,"reactive_opportunities_found":0,"hot_token_opportunities_found":0,"cross_dex_opportunities_found":0,"trades_executed":[],"errors":[],"mev_attacks":[],"competition_results":[],"scan_metrics":{"proactive_opportunities":0,"reactive_opportunities":0,"hot_token_opportunities":0,"cross_dex_opportunities":0,"total_scan_time_ms":5935}}
{"block_number":23028092,"execution_time_ms":3271,"opportunities_found":0,"proactive_opportunities_found":0,"reactive_opportunities_found":0,"hot_token_opportunities_found":0,"cross_dex_opportunities_found":0,"trades_executed":[],"errors":[],"mev_attacks":[],"competition_results":[],"scan_metrics":{"proactive_opportunities":0,"reactive_opportunities":0,"hot_token_opportunities":0,"cross_dex_opportunities":0,"total_scan_time_ms":3270}}
{"block_number":23028093,"execution_time_ms":3913,"opportunities_found":0,"proactive_opportunities_found":0,"reactive_opportunities_found":0,"hot_token_opportunities_found":0,"cross_dex_opportunities_found":0,"trades_executed":[],"errors":[],"mev_attacks":[],"competition_results":[],"scan_metrics":{"proactive_opportunities":0,"reactive_opportunities":0,"hot_token_opportunities":0,"cross_dex_opportunities":0,"total_scan_time_ms":3912}}
{"block_number":23028094,"execution_time_ms":3700,"opportunities_found":0,"proactive_opportunities_found":0,"reactive_opportunities_found":0,"hot_token_opportunities_found":0,"cross_dex_opportunities_found":0,"trades_executed":[],"errors":[],"mev_attacks":[],"competition_results":[],"scan_metrics":{"proactive_opportunities":0,"reactive_opportunities":0,"hot_token_opportunities":0,"cross_dex_opportunities":0,"total_scan_time_ms":3699}}
{"block_number":23028095,"execution_time_ms":4545,"opportunities_found":0,"proactive_opportunities_found":0,"reactive_opportunities_found":0,"hot_token_opportunities_found":0,"cross_dex_opportunities_found":0,"trades_executed":[],"errors":[],"mev_attacks":[],"competition_results":[],"scan_metrics":{"proactive_opportunities":0,"reactive_opportunities":0,"hot_token_opportunities":0,"cross_dex_opportunities":0,"total_scan_time_ms":4543}}
{"block_number":23028096,"execution_time_ms":2672,"opportunities_found":0,"proactive_opportunities_found":0,"reactive_opportunities_found":0,"hot_token_opportunities_found":0,"cross_dex_opportunities_found":0,"trades_executed":[],"errors":[],"mev_attacks":[],"competition_results":[],"scan_metrics":{"proactive_opportunities":0,"reactive_opportunities":0,"hot_token_opportunities":0,"cross_dex_opportunities":0,"total_scan_time_ms":2670}}
{"block_number":23028097,"execution_time_ms":3579,"opportunities_found":0,"proactive_opportunities_found":0,"reactive_opportunities_found":0,"hot_token_opportunities_found":0,"cross_dex_opportunities_found":0,"trades_executed":[],"errors":[],"mev_attacks":[],"competition_results":[],"scan_metrics":{"proactive_opportunities":0,"reactive_opportunities":0,"hot_token_opportunities":0,"cross_dex_opportunities":0,"total_scan_time_ms":3577}}
{"block_number":23028098,"execution_time_ms":3937,"opportunities_found":0,"proactive_opportunities_found":0,"reactive_opportunities_found":0,"hot_token_opportunities_found":0,"cross_dex_opportunities_found":0,"trades_executed":[],"errors":[],"mev_attacks":[],"competition_results":[],"scan_metrics":{"proactive_opportunities":0,"reactive_opportunities":0,"hot_token_opportunities":0,"cross_dex_opportunities":0,"total_scan_time_ms":3936}}
{"block_number":23028099,"execution_time_ms":2361,"opportunities_found":0,"proactive_opportunities_found":0,"reactive_opportunities_found":0,"hot_token_opportunities_found":0,"cross_dex_opportunities_found":0,"trades_executed":[],"errors":[],"mev_attacks":[],"competition_results":[],"scan_metrics":{"proactive_opportunities":0,"reactive_opportunities":0,"hot_token_opportunities":0,"cross_dex_opportunities":0,"total_scan_time_ms":2353}}
